<?xml version="1.0" encoding="utf-8" ?>
<publisher-upload-manifest publisher-id="694915275001" preparer="David H." report-success="TRUE">
  <notify email="ses10003@byui.edu" />

  <notify email="jdhernandezr@gmail.com" />

    <asset filename="2011_06_01_MED_MIND.mov"
        refid="asset1177741098718"
        size="117774109"
        display-name="Meditation and Mindfulness"
        encode-to="MP4"
        encode-multiple="TRUE"
        type="VIDEO_FULL"/>

    <title name="Meditation and Mindfulness"
        refid="2011_06_01_MED_MIND.mov"
        video-full-refid="asset1177741098718"
        active="TRUE">
        <short-description>I went to a meditation workshop and learned how to meditate</short-description>
        <long-description></long-description>
        <related-link-url></related-link-url>
        <related-link-text></related-link-text>
        <tag>Meditation</tag>
        <tag>I-News</tag>
        <tag>Brittany Sessions</tag>
        <tag></tag>
        <tag></tag>
    </title>

</publisher-upload-manifest>